{
  "tracks": [
    {
      "artist": "Dinos",
      "album": "Imany Deluxe",
      "track": "Placebo",
      "uri": "spotify:track:17jlkHSNHFu1zUuu8QZyOW"
    },
    {
      "artist": "Linkin Park",
      "album": "Minutes to Midnight",
      "track": "Bleed It Out",
      "uri": "spotify:track:0UFDKFqW2oGspYeYqo9wjA"
    },
    {
      "artist": "Kavinsky",
      "album": "Nightcall",
      "track": "Nightcall",
      "uri": "spotify:track:0U0ldCRmgCqhVvD6ksG63j"
    },
    {
      "artist": "CICI Zhu",
      "album": "ILLUSIONS",
      "track": "ILLUSIONS - [HARPSICHORD MIX]",
      "uri": "spotify:track:34ohtUXmLHzIBelpbEendD"
    },
    {
      "artist": "Radiohead",
      "album": "Pablo Honey",
      "track": "Creep",
      "uri": "spotify:track:70LcF31zb1H0PyJoS1Sx1r"
    },
    {
      "artist": "Brock Berrigan",
      "album": "Breaking Bread",
      "track": "Snake Eyes",
      "uri": "spotify:track:38gEinXmtxdxroRzpGY65w"
    },
    {
      "artist": "Kanye West",
      "album": "Late Registration",
      "track": "Gold Digger",
      "uri": "spotify:track:1PS1QMdUqOal0ai3Gt7sDQ"
    },
    {
      "artist": "Kalash Criminel",
      "album": "ENCORE LES PROBLÈMES",
      "track": "ENCORE LES PROBLÈMES",
      "uri": "spotify:track:4l2mk2vwThnlnOdJEzQclY"
    },
    {
      "artist": "Booba",
      "album": "0.9",
      "track": "Pourvu Qu'Elles M'Aiment",
      "uri": "spotify:track:6Hr8Ek8a7r0aIdybhEx2T2"
    },
    {
      "artist": "Central Cee",
      "album": "Doja",
      "track": "Doja",
      "uri": "spotify:track:3LtpKP5abr2qqjunvjlX5i"
    },
    {
      "artist": "Anderson .Paak",
      "album": "Bubblin",
      "track": "Bubblin",
      "uri": "spotify:track:6BvtitRX5lQC87YlA6rq0n"
    },
    {
      "artist": "Red Hot Chili Peppers",
      "album": "Stadium Arcadium",
      "track": "Dani California",
      "uri": "spotify:track:10Nmj3JCNoMeBQ87uw5j8k"
    },
    {
      "artist": "Metallica",
      "album": "Metallica",
      "track": "Nothing Else Matters",
      "uri": "spotify:track:0nLiqZ6A27jJri2VCalIUs"
    },
    {
      "artist": "Luther",
      "album": "GARÇON",
      "track": "ALAKAZAM",
      "uri": "spotify:track:3bvAmJOfhcfoAsUYFcqe2c"
    },
    {
      "artist": "Dick Dale & His Del-Tones",
      "album": "Pulp Fiction",
      "track": "Misirlou",
      "uri": "spotify:track:3538ZnMvpmpImrC6rFQgDr"
    },
    {
      "artist": "Jengi",
      "album": "Bel Mercy",
      "track": "Bel Mercy",
      "uri": "spotify:track:1635wWSdp29PO3GxYhy991"
    },
    {
      "artist": "Rock Fortune",
      "album": "Soldier of Fortune (Hip-Hop Instrumentals)",
      "track": "Soldier of Fortune (Instrumental)",
      "uri": "spotify:track:1X3FDvmx5xifwxbEo8LME7"
    },
    {
      "artist": "Nina Simone",
      "album": "Broadway-Blues-Ballads",
      "track": "Don't Let Me Be Misunderstood",
      "uri": "spotify:track:7M9pPyt8Gr41THLhbz4NSB"
    },
    {
      "artist": "Bruno Mars",
      "album": "Unorthodox Jukebox",
      "track": "Treasure",
      "uri": "spotify:track:55h7vJchibLdUkxdlX3fK7"
    },
    {
      "artist": "System Of A Down",
      "album": "Toxicity",
      "track": "Chop Suey!",
      "uri": "spotify:track:2DlHlPMa4M17kufBvI2lEN"
    },
    {
      "artist": "War",
      "album": "Why Can't We Be Friends?",
      "track": "Low Rider",
      "uri": "spotify:track:7Bz8yww6UMbTgTVLG6zbI4"
    },
    {
      "artist": "Emmit Fenn",
      "album": "The Last Dance",
      "track": "Control",
      "uri": "spotify:track:02VX51QXZlZcubvkm5mQGg"
    },
    {
      "artist": "Metro Boomin",
      "album": "HEROES & VILLAINS",
      "track": "Too Many Nights (feat. Don Toliver & with Future)",
      "uri": "spotify:track:2Hh3ETdQKrmSI3QS0hme7g"
    },
    {
      "artist": "Caballero",
      "album": "OSO",
      "track": "Polaire",
      "uri": "spotify:track:2B5LpyVHXfkTIleBg04qpV"
    },
    {
      "artist": "Meek Mill",
      "album": "Dreams and Nightmares",
      "track": "Dreams and Nightmares",
      "uri": "spotify:track:42zd6DYQ4o4SECmTITrM1U"
    },
    {
      "artist": "La Fève",
      "album": "24",
      "track": "ZAY INTRO",
      "uri": "spotify:track:5WdblAl3tJu9r7S4HzeqpZ"
    },
    {
      "artist": "Kungs",
      "album": "Layers",
      "track": "Don't You Know - Radio Edit",
      "uri": "spotify:track:5F2lWCeBZMxpo6SG1Q3PlL"
    },
    {
      "artist": "Gregory Isaacs",
      "album": "Pardon Me",
      "track": "House Of The Rising Sun",
      "uri": "spotify:track:24RqLyY2w1QDZ3GJJ4xgrj"
    },
    {
      "artist": "Creedence Clearwater Revival",
      "album": "Willy And The Poor Boys",
      "track": "Fortunate Son",
      "uri": "spotify:track:4BP3uh0hFLFRb5cjsgLqDh"
    },
    {
      "artist": "Outkast",
      "album": "Speakerboxxx/The Love Below",
      "track": "Hey Ya!",
      "uri": "spotify:track:2PpruBYCo4H7WOBJ7Q2EwM"
    },
    {
      "artist": "Tash Sultana",
      "album": "Notion",
      "track": "Jungle",
      "uri": "spotify:track:1KTObLMW9mwk2iPjP3daHb"
    },
    {
      "artist": "João Gilberto",
      "album": "Brazil",
      "track": "Cordeiro de nana",
      "uri": "spotify:track:1L9QMIM4agEbJzJiRCd9ZB"
    },
    {
      "artist": "Travis Scott",
      "album": "UTOPIA",
      "track": "I KNOW ?",
      "uri": "spotify:track:6wsqVwoiVH2kde4k4KKAFU"
    },
    {
      "artist": "Leto",
      "album": "TRAP$TAR 3",
      "track": "Préjudice",
      "uri": "spotify:track:4izmyQcssvHEpC8cCFqQam"
    },
    {
      "artist": "Le Dé",
      "album": "Delta Plane",
      "track": "Triple bicéphale",
      "uri": "spotify:track:2lGBMltMTJupKXQowsBLZP"
    },
    {
      "artist": "4 Non Blondes",
      "album": "Bigger, Better, Faster, More !",
      "track": "What's Up?",
      "uri": "spotify:track:0jWgAnTrNZmOGmqgvHhZEm"
    },
    {
      "artist": "Kanye West",
      "album": "JESUS IS KING",
      "track": "Follow God",
      "uri": "spotify:track:2QpGZOhTCHHiKmpSO9FW4h"
    },
    {
      "artist": "AC/DC",
      "album": "Back In Black",
      "track": "Shoot to Thrill",
      "uri": "spotify:track:0C80GCp0mMuBzLf3EAXqxv"
    },
    {
      "artist": "AC/DC",
      "album": "Black Ice",
      "track": "Spoilin' for a Fight",
      "uri": "spotify:track:5yx3jekDsFzX987CIHX2Yn"
    },
    {
      "artist": "Outkast",
      "album": "Stankonia",
      "track": "Ms. Jackson",
      "uri": "spotify:track:0I3q5fE6wg7LIfHGngUTnV"
    },
    {
      "artist": "Steppenwolf",
      "album": "Steppenwolf",
      "track": "Born To Be Wild",
      "uri": "spotify:track:63OFKbMaZSDZ4wtesuuq6f"
    },
    {
      "artist": "Meek Mill",
      "album": "DC4",
      "track": "Blue Notes",
      "uri": "spotify:track:7Gs3otHnZDq514kFHf0nx7"
    },
    {
      "artist": "Childish Gambino",
      "album": "\"Awaken, My Love!\"",
      "track": "Redbone",
      "uri": "spotify:track:0WtDGnWL2KrMCk0mI1Gpwz"
    },
    {
      "artist": "Booba",
      "album": "Ouest Side",
      "track": "Le Duc de Boulogne",
      "uri": "spotify:track:2iC595GPZjt28Ubpq3lLWE"
    },
    {
      "artist": "Biga*Ranx",
      "album": "Petite Marie (Fanzine Remix)",
      "track": "Petite Marie (Fanzine Remix)",
      "uri": "spotify:track:4HXOC6HwBZWZ7RrSe54VuI"
    },
    {
      "artist": "Selah Sue",
      "album": "Crazy Vibes (Street Remix)",
      "track": "Crazy Vibes - Street Remix",
      "uri": "spotify:track:40R64P1s2kqw5iOgBnjXKz"
    },
    {
      "artist": "Le Dé",
      "album": "Delta Plane",
      "track": "Liège, Liège",
      "uri": "spotify:track:0SF18FF3dUs9JwGxPjfGsS"
    },
    {
      "artist": "Gnarls Barkley",
      "album": "St. Elsewhere",
      "track": "Crazy",
      "uri": "spotify:track:1vxw6aYJls2oq3gW0DujAo"
    },
    {
      "artist": "Guizmo",
      "album": "C'est tout.",
      "track": "C'est tout",
      "uri": "spotify:track:5tgOWODhYf8CpVUyStG6Sm"
    },
    {
      "artist": "Afroman",
      "album": "The Good Times",
      "track": "Crazy Rap (Colt 45 & 2 Zig Zags)",
      "uri": "spotify:track:1ACZpHI5vZ5Ea4xGlkdGWM"
    },
    {
      "artist": "Le Dé",
      "album": "Delta Plane",
      "track": "Beurre de Marrakech",
      "uri": "spotify:track:1SDIabdmQtig8TuidwkivH"
    },
    {
      "artist": "Eminem",
      "album": "Houdini",
      "track": "Houdini",
      "uri": "spotify:track:2HYFX63wP3otVIvopRS99Z"
    },
    {
      "artist": "SoulChef",
      "album": "Escapism",
      "track": "Write This Down",
      "uri": "spotify:track:10yBOZi6cIDeJOlb7Pbz1J"
    },
    {
      "artist": "Bronski Beat",
      "album": "The Age of Consent",
      "track": "Smalltown Boy",
      "uri": "spotify:track:5vmRQ3zELMLUQPo2FLQ76x"
    },
    {
      "artist": "Luther",
      "album": "GARÇON",
      "track": "TORIEL - VENI VIDI VIDE",
      "uri": "spotify:track:2EriWBuBVODGuSF5PMO29I"
    },
    {
      "artist": "Linkin Park",
      "album": "Meteora",
      "track": "Somewhere I Belong",
      "uri": "spotify:track:3fjmSxt0PskST13CSdBUFx"
    },
    {
      "artist": "Pink Floyd",
      "album": "The Dark Side Of The Moon",
      "track": "Brain Damage - 2011 Remastered Version",
      "uri": "spotify:track:7EUEl5wJb8VI777UAUvRnH"
    },
    {
      "artist": "Coldplay",
      "album": "Viva La Vida or Death and All His Friends",
      "track": "Viva La Vida",
      "uri": "spotify:track:1mea3bSkSGXuIRvnydlB5b"
    },
    {
      "artist": "Gorillaz",
      "album": "Demon Days",
      "track": "Feel Good Inc.",
      "uri": "spotify:track:0d28khcov6AiegSCpG5TuT"
    },
    {
      "artist": "Kaaris",
      "album": "Le bruit de mon âme",
      "track": "Zone de transit",
      "uri": "spotify:track:0m054qw8iB9a9C8zaqkwAr"
    },
    {
      "artist": "Boztown",
      "album": "Where You Go",
      "track": "Instant Playa",
      "uri": "spotify:track:6KPMWwKVBcRtVIwuz2SafV"
    },
    {
      "artist": "Lupe Fiasco",
      "album": "Lupe Fiasco's Food & Liquor",
      "track": "Daydreamin' (feat. Jill Scott)",
      "uri": "spotify:track:50M2QjfSM82wkJ1d0iV4mh"
    },
    {
      "artist": "Elvis Presley",
      "album": "Elvis Presley",
      "track": "Blue Suede Shoes",
      "uri": "spotify:track:47gmoUrZV3w20JAnQOZMcO"
    },
    {
      "artist": "JAY-Z",
      "album": "The Black Album",
      "track": "Lucifer",
      "uri": "spotify:track:05VHidqx1tV6V7MsCdAIby"
    },
    {
      "artist": "Daft Punk",
      "album": "Discovery",
      "track": "Aerodynamic",
      "uri": "spotify:track:3H3cOQ6LBLSvmcaV7QkZEu"
    },
    {
      "artist": "Deep Purple",
      "album": "The Platinum Collection",
      "track": "Soldier of Fortune",
      "uri": "spotify:track:7uRcUUmZpU4YVZFNVZnyXd"
    },
    {
      "artist": "Kendrick Lamar",
      "album": "good kid, m.A.A.d city",
      "track": "Money Trees",
      "uri": "spotify:track:74tLlkN3rgVzRqQJgPfink"
    },
    {
      "artist": "Modjo",
      "album": "Modjo",
      "track": "Lady - Hear Me Tonight",
      "uri": "spotify:track:49X0LAl6faAusYq02PRAY6"
    },
    {
      "artist": "Kendrick Lamar",
      "album": "Not Like Us",
      "track": "Not Like Us",
      "uri": "spotify:track:6AI3ezQ4o3HUoP6Dhudph3"
    },
    {
      "artist": "BoyWithUke",
      "album": "Serotonin Dreams",
      "track": "Toxic",
      "uri": "spotify:track:3M214U0mwSm041GsQR3nrO"
    },
    {
      "artist": "Travis Scott",
      "album": "The Hate U Give",
      "track": "Goosebumps",
      "uri": "spotify:track:6dWf1xaHOmJo7eL9WuSkdL"
    },
    {
      "artist": "The Notorious B.I.G.",
      "album": "Greatest Hits",
      "track": "Big Poppa - 2007 Remaster",
      "uri": "spotify:track:63BcfK6YAzJYeISaTPr6IO"
    },
    {
      "artist": "Watermät",
      "album": "Bullit",
      "track": "Bullit - Radio Edit",
      "uri": "spotify:track:4rlvA61wV9htmVXEftARoU"
    },
    {
      "artist": "Kavinsky",
      "album": "Reborn",
      "track": "Renegade",
      "uri": "spotify:track:0tXzxt3aJcfKu9L5i7tgfK"
    },
    {
      "artist": "Hippocampe Fou",
      "album": "Aquatrip",
      "track": "Aquatrip",
      "uri": "spotify:track:4VZhlN99UoRLx3eaYwIaxg"
    },
    {
      "artist": "Connor Price",
      "album": "Trendsetter",
      "track": "Trendsetter",
      "uri": "spotify:track:09VW2o6EHSWwzCdhW4ARU1"
    },
    {
      "artist": "Joy Crookes",
      "album": "Feet Don't Fail Me Now",
      "track": "Feet Don't Fail Me Now",
      "uri": "spotify:track:1GVkrFVc94CTjm9bdSmGjp"
    },
    {
      "artist": "Tommy Richman",
      "album": "MILLION DOLLAR BABY",
      "track": "MILLION DOLLAR BABY",
      "uri": "spotify:track:5AJ9hqTS2wcFQCELCFRO7A"
    },
    {
      "artist": "Booba",
      "album": "Nero nemesis",
      "track": "92i veyron",
      "uri": "spotify:track:6Wpgf0xNuBIUpJF2uH7swL"
    },
    {
      "artist": "Prznt",
      "album": "Alone",
      "track": "Alone",
      "uri": "spotify:track:62ncBoXWboKUXKZcQMLtSD"
    },
    {
      "artist": "JAY-Z",
      "album": "Watch The Throne",
      "track": "Ni**as In Paris",
      "uri": "spotify:track:1auxYwYrFRqZP7t3s7w4um"
    },
    {
      "artist": "Jul",
      "album": "La zone en personne",
      "track": "Et je deviens fou",
      "uri": "spotify:track:6PTvE2gQraGPgXUGmYhvwV"
    },
    {
      "artist": "Polo & Pan",
      "album": "Ani Kuni",
      "track": "Ani Kuni",
      "uri": "spotify:track:12QphPukpWDR9w1iimddfP"
    },
    {
      "artist": "Kanye West",
      "album": "My Beautiful Dark Twisted Fantasy",
      "track": "POWER",
      "uri": "spotify:track:2gZUPNdnz5Y45eiGxpHGSc"
    },
    {
      "artist": "Flight Facilities",
      "album": "Down To Earth",
      "track": "Crave You",
      "uri": "spotify:track:4MWmpfC07n0lJ9lwOFXrak"
    },
    {
      "artist": "Key Glock",
      "album": "Yellow Tape 2",
      "track": "Ambition For Cash",
      "uri": "spotify:track:4mIHgQ3ofK2RK34UdbqMbe"
    },
    {
      "artist": "Bratia Stereo",
      "album": "Ayayay (feat. Tony Tonite)",
      "track": "Ayayay",
      "uri": "spotify:track:4eW1hdI2gqGCnGyJbxuypD"
    },
    {
      "artist": "Ziak",
      "album": "Chrome",
      "track": "Même pas un grincement",
      "uri": "spotify:track:2MQuAyJthNIHzSLNGR3WMm"
    },
    {
      "artist": "The Beatles",
      "album": "Love",
      "track": "Hey Jude",
      "uri": "spotify:track:1eT2CjXwFXNx6oY5ydvzKU"
    },
    {
      "artist": "310babii",
      "album": "soak city (do it)",
      "track": "soak city (do it)",
      "uri": "spotify:track:5C8h9PY9oTneqJihbn10NB"
    },
    {
      "artist": "Jul",
      "album": "Dans ma paranoïa",
      "track": "Tout seul",
      "uri": "spotify:track:3JrpHIP4DbKrBmk9zBmnJO"
    },
    {
      "artist": "James Brown",
      "album": "Motherlode",
      "track": "People Get Up And Drive Your Funky Soul - Remix",
      "uri": "spotify:track:5U3i59kbTLrxo46TU1FRnF"
    },
    {
      "artist": "Busy P",
      "album": "Rainbow Man 2.0",
      "track": "Rainbow Man",
      "uri": "spotify:track:3ZutS6kzYIHQknkuuHtpUP"
    },
    {
      "artist": "Davodka",
      "album": "Accusé de réflexion",
      "track": "Accusé de réflexion chapitre 2",
      "uri": "spotify:track:729tShstlDCEdXSR4nORu2"
    },
    {
      "artist": "bar italia",
      "album": "The Twits",
      "track": "twist",
      "uri": "spotify:track:5xODaw1CaAZHZ0MwTWKUt0"
    },
    {
      "artist": "White Town",
      "album": "Women in Technology",
      "track": "Your Woman",
      "uri": "spotify:track:3UBItNVbFQiVC5hBQlBvnr"
    },
    {
      "artist": "Népal",
      "album": "2016 - 2018",
      "track": "Babylone",
      "uri": "spotify:track:2j494b1ZhXswDVorEIV5va"
    },
    {
      "artist": "Ozzy Osbourne",
      "album": "No More Tears (Expanded Edition)",
      "track": "No More Tears",
      "uri": "spotify:track:7w6PJe5KBPyvuRYxFkPssC"
    },
    {
      "artist": "Flowindz",
      "album": "Falling",
      "track": "Falling",
      "uri": "spotify:track:0yxjyIPRpre2Cb67RnUTW7"
    },
    {
      "artist": "Billy Joel",
      "album": "The Stranger (Legacy Edition)",
      "track": "Vienna",
      "uri": "spotify:track:4U45aEWtQhrm8A5mxPaFZ7"
    },
    {
      "artist": "Howlin' Wolf",
      "album": "The London Howlin’ Wolf Sessions",
      "track": "Killing Floor - London Revisited Version",
      "uri": "spotify:track:2EZSfrALQ4qzqKll2kQJOl"
    },
    {
      "artist": "Kanye West",
      "album": "Graduation",
      "track": "Stronger",
      "uri": "spotify:track:0j2T0R9dR9qdJYsB7ciXhf"
    },
    {
      "artist": "Blarg",
      "album": "Mach Was Du Denkst",
      "track": "Don't Stop Alice",
      "uri": "spotify:track:2IE3FGuErMCKXurZf9DF68"
    },
    {
      "artist": "Kendrick Lamar",
      "album": "DAMN.",
      "track": "DNA.",
      "uri": "spotify:track:6HZILIRieu8S0iqY8kIKhj"
    },
    {
      "artist": "Moderator",
      "album": "The World Within (Deluxe)",
      "track": "Words Remain",
      "uri": "spotify:track:1AW4amyytwC0JNVmpVngIN"
    },
    {
      "artist": "Busta Rhymes",
      "album": "It Ain't Safe No More. . .",
      "track": "I Know What You Want (feat. Flipmode Squad)",
      "uri": "spotify:track:0YImOCkIJ2PWhCXaURCZnY"
    },
    {
      "artist": "Blue Swede",
      "album": "Hooked On A Feeling",
      "track": "Hooked On A Feeling",
      "uri": "spotify:track:6Ac4NVYYl2U73QiTt11ZKd"
    },
    {
      "artist": "Pink Floyd",
      "album": "The Dark Side Of The Moon",
      "track": "Eclipse - 2011 Remastered Version",
      "uri": "spotify:track:3Z2RsIdWm4BNbT0LsFBuoN"
    },
    {
      "artist": "The Wailers",
      "album": "Burnin'",
      "track": "Burnin' And Lootin'",
      "uri": "spotify:track:34Jqj42hsT3O3N8yihE3B6"
    },
    {
      "artist": "Coolio",
      "album": "Gangsta's Paradise",
      "track": "Gangsta's Paradise",
      "uri": "spotify:track:1DIXPcTDzTj8ZMHt3PDt8p"
    },
    {
      "artist": "Bad Boys Blue",
      "album": "Hot Girls, Bad Boys",
      "track": "You're a Woman",
      "uri": "spotify:track:1oP3OXN5VK57w5UveOjZmW"
    },
    {
      "artist": "Rodríguez",
      "album": "Cold Fact",
      "track": "Sugar Man",
      "uri": "spotify:track:17nOJOcPbcl4sKzM2yyYDp"
    },
    {
      "artist": "Red Hot Chili Peppers",
      "album": "By the Way",
      "track": "Can't Stop",
      "uri": "spotify:track:3ZOEytgrvLwQaqXreDs2Jx"
    },
    {
      "artist": "Guizmo",
      "album": "Lamine",
      "track": "Manifeste",
      "uri": "spotify:track:6GMZJA5MOO8qvFI2xZPYXf"
    },
    {
      "artist": "Skrillex",
      "album": "Bangarang EP",
      "track": "Kyoto (feat. Sirah)",
      "uri": "spotify:track:3FUZpoj9VV0sgc8RqbS3xQ"
    },
    {
      "artist": "Metro Boomin",
      "album": "NOT ALL HEROES WEAR CAPES",
      "track": "Space Cadet (feat. Gunna)",
      "uri": "spotify:track:1fewSx2d5KIZ04wsooEBOz"
    },
    {
      "artist": "Bakermat",
      "album": "The Ringmaster",
      "track": "Baianá",
      "uri": "spotify:track:780be5fB7823aHG06mwTat"
    },
    {
      "artist": "Prince of Falls",
      "album": "Till We Feel Something",
      "track": "Marlboro",
      "uri": "spotify:track:5e8yGIFZEt73yKPMLiKHKo"
    },
    {
      "artist": "Norman Greenbaum",
      "album": "Spirit In The Sky",
      "track": "Spirit In The Sky - Deluxe Edition",
      "uri": "spotify:track:0jvN7eQJJt4nxQzgQfZ1SP"
    },
    {
      "artist": "Radiohead",
      "album": "Creep EP",
      "track": "Creep - Acoustic",
      "uri": "spotify:track:6JpjIy1M7oxvPJ3uVdUKTe"
    },
    {
      "artist": "JID",
      "album": "The Forever Story",
      "track": "Surround Sound (feat. 21 Savage & Baby Tate)",
      "uri": "spotify:track:1udwFobQ1JoOdWPQrp2b6u"
    },
    {
      "artist": "Kanye West",
      "album": "The Life Of Pablo",
      "track": "Famous",
      "uri": "spotify:track:19a3JfW8BQwqHWUMbcqSx8"
    },
    {
      "artist": "21 Savage",
      "album": "american dream",
      "track": "prove it",
      "uri": "spotify:track:5wttBUDyaHAR5q9fYnN3YF"
    },
    {
      "artist": "Le Dé",
      "album": "Streamz",
      "track": "Streamz",
      "uri": "spotify:track:16jwdHHcMnnzXuaVs6b9tT"
    },
    {
      "artist": "Dooz Kawa",
      "album": "Bohemian Rap Story",
      "track": "Me faire la belle",
      "uri": "spotify:track:7Dg6YSfLTADFX1t0Nszy5B"
    },
    {
      "artist": "Justice",
      "album": "Justice",
      "track": "Genesis",
      "uri": "spotify:track:4wSmqFg31t6LsQWtzYAJob"
    },
    {
      "artist": "Trinix Remix",
      "album": "Amaphupho",
      "track": "Amaphupho",
      "uri": "spotify:track:7efYgNo2ROxBQszftKdG7v"
    },
    {
      "artist": "The Notorious B.I.G.",
      "album": "Whos The Man ? Soundtrack",
      "track": "Party And Bullshit",
      "uri": "spotify:track:5mqPg2dyqb1gBNyg9ycGcT"
    },
    {
      "artist": "Nirvana",
      "album": "MTV Unplugged In New York",
      "track": "Where Did You Sleep Last Night - Live",
      "uri": "spotify:track:551qy5vUgrUfEUc4dCNfht"
    },
    {
      "artist": "Rage Against The Machine",
      "album": "Rage Against The Machine - XX (20th Anniversary Special Edition)",
      "track": "Killing In The Name",
      "uri": "spotify:track:59WN2psjkt1tyaxjspN8fp"
    },
    {
      "artist": "Justice",
      "album": "D.A.N.C.E.",
      "track": "D.A.N.C.E. - Logic Reprise",
      "uri": "spotify:track:5qz9QTNgiajpsnp7agqBpc"
    },
    {
      "artist": "Møme",
      "album": "Panorama",
      "track": "Aloha",
      "uri": "spotify:track:7IfOWyh4jTfkcGVrXKVNq0"
    },
    {
      "artist": "Booba",
      "album": "Temps mort",
      "track": "Jusqu'ici tout va bien",
      "uri": "spotify:track:17Brxsp87dg12UkXZaqh5q"
    },
    {
      "artist": "Mike Posner",
      "album": "31 Minutes to Takeoff",
      "track": "Cooler Than Me - Single Mix",
      "uri": "spotify:track:2V4bv1fNWfTcyRJKmej6Sj"
    },
    {
      "artist": "Bob Marley & The Wailers",
      "album": "Exodus",
      "track": "Three Little Birds",
      "uri": "spotify:track:7yFvSYKk3g5g8e7Ffl16ws"
    },
    {
      "artist": "Booba",
      "album": "AD VITAM ÆTERNAM",
      "track": "Saga",
      "uri": "spotify:track:0Cnw4vb7xbbl6bkUaDcMaJ"
    },
    {
      "artist": "Hugo TSR",
      "album": "Une vie et quelques",
      "track": "Périmètre",
      "uri": "spotify:track:7LHdmc48cp4RxOOih1QrgR"
    },
    {
      "artist": "PJ",
      "album": "Everything In Its Right Place (House)",
      "track": "Everything In Its Right Place (House)",
      "uri": "spotify:track:2pxLbGMGoeWlpuxdciBkXf"
    },
    {
      "artist": "Hippie Sabotage",
      "album": "Providence",
      "track": "Devil Eyes",
      "uri": "spotify:track:7MiZjKawmXTsTNePyTfPyL"
    },
    {
      "artist": "Gorillaz",
      "album": "Demon Days",
      "track": "O Green World",
      "uri": "spotify:track:4hNPMfFHauPIbOKvdYqFt7"
    },
    {
      "artist": "Chemical Surf",
      "album": "Hey Hey Hey",
      "track": "Hey Hey Hey",
      "uri": "spotify:track:571lcLQWO5cclITS1FtCM5"
    },
    {
      "artist": "Kali Uchis",
      "album": "Moonlight",
      "track": "Moonlight",
      "uri": "spotify:track:2i2gDpKKWjvnRTOZRhaPh2"
    },
    {
      "artist": "PNL",
      "album": "Le monde Chico",
      "track": "Mexico",
      "uri": "spotify:track:4di2vpRLHHZ5u4UtlTMiNZ"
    },
    {
      "artist": "Gorillaz",
      "album": "Demon Days",
      "track": "Fire Coming out of the Monkey's Head",
      "uri": "spotify:track:1S9tfxdFr4TqoqA14gnKj3"
    },
    {
      "artist": "Eminem",
      "album": "The Marshall Mathers LP",
      "track": "Stan",
      "uri": "spotify:track:3UmaczJpikHgJFyBTAJVoz"
    },
    {
      "artist": "Tsonpa",
      "album": "Freestyle Funk",
      "track": "Freestyle Funk",
      "uri": "spotify:track:61hO3dj5FoWM4MprDoCE3r"
    },
    {
      "artist": "Luidji",
      "album": "Foufoune Palace",
      "track": "Foufoune Palace",
      "uri": "spotify:track:1PS1iGV5JL3hLwtRgI7zFo"
    },
    {
      "artist": "Yamê",
      "album": "ELOWI",
      "track": "Call of Valhalla",
      "uri": "spotify:track:6hShO2ZZ0bFO1SNfpfkHOD"
    },
    {
      "artist": "The Game",
      "album": "Jesus Piece",
      "track": "Ali Bomaye",
      "uri": "spotify:track:0LFcFGLYTX6UmeIdO7NVd7"
    },
    {
      "artist": "Hotel Ugly",
      "album": "Shut up My Moms Calling",
      "track": "Shut up My Moms Calling",
      "uri": "spotify:track:3hxIUxnT27p5WcmjGUXNwx"
    },
    {
      "artist": "Three Dog Night",
      "album": "Naturally",
      "track": "Joy To The World",
      "uri": "spotify:track:2ymeOsYijJz09LfKw3yM2x"
    },
    {
      "artist": "Omar Woods",
      "album": "Don't Wait For Me",
      "track": "Don't Wait For Me",
      "uri": "spotify:track:2WewN3ZncjQxJ3HKfmqFOA"
    },
    {
      "artist": "Damso",
      "album": "Ipséité",
      "track": "Γ. Mosaïque solitaire",
      "uri": "spotify:track:7wFK2ReVQpq80IAGs6eI1l"
    },
    {
      "artist": "TIF",
      "album": "1.6",
      "track": "SHADOW BOXING - LIVE SESSION",
      "uri": "spotify:track:6o4bhv6Ke086V7inAPUDv7"
    },
    {
      "artist": "The Blaze",
      "album": "TERRITORY",
      "track": "TERRITORY",
      "uri": "spotify:track:2W3EgJst61RLZtPPm3EQim"
    },
    {
      "artist": "Guizmo",
      "album": "Dans ma ruche",
      "track": "André",
      "uri": "spotify:track:14WuWxuKmGsNTD7wXEt1jH"
    },
    {
      "artist": "Else",
      "album": "Pacific",
      "track": "Pacific 704",
      "uri": "spotify:track:15K8YkotxPtpu7R8qMd5EJ"
    },
    {
      "artist": "AppleHoule",
      "album": "Soccer Blocker",
      "track": "Soccer Blocker",
      "uri": "spotify:track:7BKixPEyhDrVI5QQOGiM5S"
    },
    {
      "artist": "Kool & The Gang",
      "album": "Celebrate!",
      "track": "Celebration",
      "uri": "spotify:track:3K7Q9PHUWPTaknlbFPThn2"
    },
    {
      "artist": "Pigeon John",
      "album": "Dragon Slayer",
      "track": "The Bomb - Single version",
      "uri": "spotify:track:2JUoEXXQxjjBfISZxycyFt"
    },
    {
      "artist": "The Notorious B.I.G.",
      "album": "Greatest Hits",
      "track": "Get Money (feat. Junior M.A.F.I.A.) - 2007 Remaster",
      "uri": "spotify:track:3PA9dH8cT0wR5UW4XkC44Y"
    },
    {
      "artist": "Prinsess Jorge",
      "album": "Natural",
      "track": "Natural",
      "uri": "spotify:track:3OKAYvfvOvxqZQk3KBCIZr"
    },
    {
      "artist": "Damso",
      "album": "QALF infinity",
      "track": "DEUX TOILES DE MER",
      "uri": "spotify:track:6jabQbZ67ACJufvKSv0DI1"
    },
    {
      "artist": "Mister You",
      "album": "Dans Ma Grotte",
      "track": "30 JUIN 2009",
      "uri": "spotify:track:2IhZelVn4t2c6GeGeIsvz2"
    },
    {
      "artist": "Hindi Zahra",
      "album": "Handmade",
      "track": "Beautiful Tango - Unplugged",
      "uri": "spotify:track:1AAmQJO43qsQGc1pWRmTxN"
    },
    {
      "artist": "William Araujo",
      "album": "VV",
      "track": "Tempo",
      "uri": "spotify:track:0g16nAyRYfpiTcfGv8ghLF"
    },
    {
      "artist": "Linkin Park",
      "album": "Meteora 20th Anniversary Edition",
      "track": "Fighting Myself",
      "uri": "spotify:track:2ipYQ6pcabz1NovVrr9LKH"
    },
    {
      "artist": "Agnes Nunes",
      "album": "O Amor e Suas Variáveis",
      "track": "Coração Marruá",
      "uri": "spotify:track:66r0hgaeMw64dPebjGldX3"
    },
    {
      "artist": "The Supermen Lovers",
      "album": "Starlight",
      "track": "Starlight - Radio Edit",
      "uri": "spotify:track:4UfupbARPxljVkBmuZlJnY"
    },
    {
      "artist": "Ice Cube",
      "album": "Lethal Injection",
      "track": "You Know How We Do It",
      "uri": "spotify:track:2Ih217RCGAmyQR68Nn7Cqo"
    },
    {
      "artist": "20syl",
      "album": "Inertia",
      "track": "Inertia",
      "uri": "spotify:track:1jLi3qBm7GbTiHx3trcTQk"
    },
    {
      "artist": "The Weeknd",
      "album": "Often",
      "track": "Often - Kygo Remix",
      "uri": "spotify:track:27NV2KxoQ8WuLMqlTDI61F"
    },
    {
      "artist": "Bee Gees",
      "album": "Staying Alive",
      "track": "Stayin' Alive",
      "uri": "spotify:track:4UDmDIqJIbrW0hMBQMFOsM"
    },
    {
      "artist": "Justice",
      "album": "Hyperdrama",
      "track": "Neverender",
      "uri": "spotify:track:3aQ9MHkMeL7Yu7jpyF62xn"
    },
    {
      "artist": "Luciano",
      "album": "Seductive",
      "track": "Blue Porsche (feat. Niska)",
      "uri": "spotify:track:706vAFbkJSTXJzxWs50l4y"
    },
    {
      "artist": "System Of A Down",
      "album": "Toxicity",
      "track": "Toxicity",
      "uri": "spotify:track:0snQkGI5qnAmohLE7jTsTn"
    },
    {
      "artist": "A$AP Rocky",
      "album": "AT.LONG.LAST.A$AP",
      "track": "Everyday (feat. Rod Stewart, Miguel & Mark Ronson)",
      "uri": "spotify:track:2N3U8uTYhjX2KwGT0pf5x0"
    },
    {
      "artist": "Eminem",
      "album": "The Eminem Show",
      "track": "Without Me",
      "uri": "spotify:track:7lQ8MOhq6IN2w8EYcFNSUk"
    },
    {
      "artist": "Kendrick Lamar",
      "album": "DAMN.",
      "track": "HUMBLE.",
      "uri": "spotify:track:7KXjTSCq5nL1LoYtL7XAwS"
    },
    {
      "artist": "Madcon",
      "album": "Beggin",
      "track": "Beggin - Original Version",
      "uri": "spotify:track:7eXrGBrl1mBKhxlWX0IoOQ"
    },
    {
      "artist": "Eslabon Armado",
      "album": "Ella Baila Sola",
      "track": "Ella Baila Sola",
      "uri": "spotify:track:3dnP0JxCgygwQH9Gm7q7nb"
    },
    {
      "artist": "Delinquent Habits",
      "album": "Merry Go Round",
      "track": "Return Of The Tres",
      "uri": "spotify:track:5qVF2rEf75oPrZHhmZmDKk"
    },
    {
      "artist": "Rodríguez",
      "album": "Cold Fact",
      "track": "Hate Street Dialogue",
      "uri": "spotify:track:3Y0iZyngvwiGF15eLRttN7"
    },
    {
      "artist": "Yamê",
      "album": "ELOWI",
      "track": "Ayo Mba",
      "uri": "spotify:track:0dlSTSgnQQoe6xJA5cO0IM"
    },
    {
      "artist": "Israel Kamakawiwo'ole",
      "album": "Somewhere Over the Rainbow The Best of Israel Kamakawiwo`ole",
      "track": "Over the Rainbow",
      "uri": "spotify:track:4yDjzVhXig9tfO7Zv46FE8"
    },
    {
      "artist": "Trinix Remix",
      "album": "Figa",
      "track": "Figa",
      "uri": "spotify:track:6EkrsqZTNnOhlX3mys2VyR"
    },
    {
      "artist": "Joey Bada$$",
      "album": "Love Is Only a Feeling",
      "track": "Love Is Only a Feeling",
      "uri": "spotify:track:7umZiitjVsEjMQ6HNddpUI"
    },
    {
      "artist": "Lomepal",
      "album": "Mauvais Ordre",
      "track": "Decrescendo",
      "uri": "spotify:track:4otT81iBBpaf36roGtzT4a"
    },
    {
      "artist": "Gorillaz",
      "album": "Plastic Beach",
      "track": "On Melancholy Hill",
      "uri": "spotify:track:0q6LuUqGLUiCPP1cbdwFs3"
    },
    {
      "artist": "Jeune Lion",
      "album": "BABYLONE BRÛLE",
      "track": "BABYLONE BRÛLE",
      "uri": "spotify:track:4G38acx9dGit85Wvgupp1X"
    },
    {
      "artist": "Avicii",
      "album": "True",
      "track": "Addicted To You",
      "uri": "spotify:track:4eDYMhIin1pSLIG96f1aD0"
    },
    {
      "artist": "The Clash",
      "album": "Combat Rock (Remastered)",
      "track": "Should I Stay or Should I Go - Remastered",
      "uri": "spotify:track:39shmbIHICJ2Wxnk1fPSdz"
    },
    {
      "artist": "Volodia",
      "album": "La canopée",
      "track": "La canopée",
      "uri": "spotify:track:455HcaRfpFFjXjXOG8ukqe"
    },
    {
      "artist": "Jim Croce",
      "album": "Photographs & Memories: His Greatest Hits",
      "track": "Time in a Bottle",
      "uri": "spotify:track:20A2Xe76p9wxUFLbbzZjTM"
    },
    {
      "artist": "Toots & The Maytals",
      "album": "Funky Kingston",
      "track": "Funky Kingston",
      "uri": "spotify:track:26WPI2aksB9XdqmeLfca5z"
    },
    {
      "artist": "Elliott Smith",
      "album": "XO",
      "track": "Miss Misery",
      "uri": "spotify:track:4zetUxeSCCDwrr1jJT0SuD"
    },
    {
      "artist": "Yamê",
      "album": "Bécane - A COLORS SHOW",
      "track": "Bécane - A COLORS SHOW",
      "uri": "spotify:track:3oUEzTAoOxqZHN4xiqTGqJ"
    },
    {
      "artist": "Masego",
      "album": "Navajo",
      "track": "Navajo",
      "uri": "spotify:track:6zWU7YALeEDMcPGhKKZJhV"
    },
    {
      "artist": "Arctic Monkeys",
      "album": "AM",
      "track": "Do I Wanna Know?",
      "uri": "spotify:track:5FVd6KXrgO9B3JPmC8OPst"
    },
    {
      "artist": "Beach Weather",
      "album": "Pineapple Sunrise",
      "track": "Sex, Drugs, Etc.",
      "uri": "spotify:track:7MlDNspYwfqnHxORufupwq"
    },
    {
      "artist": "Nenei",
      "album": "Just the Two of Us",
      "track": "Just the Two of Us - Luxury Remix",
      "uri": "spotify:track:4tiTsHvHxcEmWeXC8tCoPt"
    },
    {
      "artist": "20syl",
      "album": "36 (Beats & Types)",
      "track": "Ode to Odd",
      "uri": "spotify:track:5boanH5wwSZfW4OiXTh0Pz"
    },
    {
      "artist": "Kavinsky",
      "album": "Nightcall",
      "track": "Pacific Coast Highway",
      "uri": "spotify:track:5GDzL9A3IihC8zm00RlH6Q"
    },
    {
      "artist": "FloyyMenor",
      "album": "Gata Only",
      "track": "Gata Only",
      "uri": "spotify:track:6XjDF6nds4DE2BBbagZol6"
    },
    {
      "artist": "Daft Punk",
      "album": "Discovery",
      "track": "Voyager",
      "uri": "spotify:track:7cMFjxhbXBpOlais7KMF3j"
    },
    {
      "artist": "Booba",
      "album": "Ouest Side",
      "track": "Mauvais garçon",
      "uri": "spotify:track:1cz0uv11TMfI6ZpOLRN9FL"
    },
    {
      "artist": "Pink Floyd",
      "album": "The Dark Side Of The Moon",
      "track": "Breathe (In The Air) - 2011 Remastered Version",
      "uri": "spotify:track:3zJRvtQkHQRTNEXSY8jQPR"
    },
    {
      "artist": "French 79",
      "album": "Olympic",
      "track": "Lovin' Feeling",
      "uri": "spotify:track:5pxtj7cCnv2hZe6mbS2MBx"
    },
    {
      "artist": "Sam & Dave",
      "album": "Hold On, I'm Comin'",
      "track": "Hold On, I'm Comin'",
      "uri": "spotify:track:6PgVDY8GTkxF3GmhVGPzoB"
    },
    {
      "artist": "Senbeï",
      "album": "Tōitsu II",
      "track": "Débordement",
      "uri": "spotify:track:30QapT5HaPtCKV3KFyudds"
    },
    {
      "artist": "Jidanofu",
      "album": "Drink A Yak",
      "track": "Drink A Yak",
      "uri": "spotify:track:5Ht48BadOqg22f3lWQLLa8"
    },
    {
      "artist": "Enur",
      "album": "Calabria 2007",
      "track": "Calabria 2007 - Radio Mix",
      "uri": "spotify:track:1aEzSaaNpTmgxDsGfMnfHO"
    },
    {
      "artist": "BigXthaPlug",
      "album": "THE BIGGEST",
      "track": "Back On My BS",
      "uri": "spotify:track:7hrFCoyWwKep7qp1lP4oga"
    },
    {
      "artist": "Wax Tailor",
      "album": "Tales of the Forgotten Melodies",
      "track": "Que Sera",
      "uri": "spotify:track:6TSDRzJGwbK9cajVbtqlPV"
    },
    {
      "artist": "Guns N' Roses",
      "album": "Use Your Illusion II",
      "track": "Knockin' On Heaven's Door",
      "uri": "spotify:track:4JiEyzf0Md7KEFFGWDDdCr"
    },
    {
      "artist": "Heuss L'enfoiré",
      "album": "En esprit",
      "track": "Hakan Sukur",
      "uri": "spotify:track:0EE5QfsVywpj6CycOUADk1"
    },
    {
      "artist": "Linkin Park",
      "album": "Meteora",
      "track": "Faint",
      "uri": "spotify:track:4Yf5bqU3NK4kNOypcrLYwU"
    },
    {
      "artist": "Sheck Wes",
      "album": "MUDBOY",
      "track": "Mo Bamba",
      "uri": "spotify:track:1xzBco0xcoJEDXktl7Jxrr"
    },
    {
      "artist": "Pink Martini",
      "album": "Sympathique",
      "track": "Amado Mio",
      "uri": "spotify:track:19tIdetwOIKsxSjaFxawvk"
    },
    {
      "artist": "21 Savage",
      "album": "american dream",
      "track": "red sky",
      "uri": "spotify:track:4yLyVdEqV790aIXyGif85v"
    },
    {
      "artist": "Booba",
      "album": "Autopsie 0",
      "track": "Scarface",
      "uri": "spotify:track:2lIBT5vhgGXKMUoCFeFJvZ"
    },
    {
      "artist": "Nas",
      "album": "Illmatic",
      "track": "N.Y. State of Mind",
      "uri": "spotify:track:0trHOzAhNpGCsGBEu7dOJo"
    },
    {
      "artist": "Robbie Williams",
      "album": "Escapology",
      "track": "Feel",
      "uri": "spotify:track:2Ms33RTRCT6gArrpcrPxmo"
    },
    {
      "artist": "Akshin Alizadeh",
      "album": "Street Bangerz Volume 8",
      "track": "Southern Man",
      "uri": "spotify:track:29MvtOnoAULKQfEKAPCbja"
    },
    {
      "artist": "Akon",
      "album": "Trouble",
      "track": "Locked Up",
      "uri": "spotify:track:0YUrjFy4qFKOO5NhM9tYdV"
    },
    {
      "artist": "Zakes Bantwini",
      "album": "Osama",
      "track": "Osama - Bruno Be, Ralk Rework",
      "uri": "spotify:track:3pWC9DZvy8N8CUHKJJ8dBp"
    },
    {
      "artist": "Disiz",
      "album": "L’Amour",
      "track": "RENCONTRE",
      "uri": "spotify:track:2toEys3zZ8rRB242Na7FZh"
    },
    {
      "artist": "Akon",
      "album": "Trouble Deluxe Edition",
      "track": "Lonely",
      "uri": "spotify:track:4v7DCN09hgXkKazefkznDQ"
    },
    {
      "artist": "Future",
      "album": "Life Is Good (feat. Drake)",
      "track": "Life Is Good (feat. Drake)",
      "uri": "spotify:track:5yY9lUy8nbvjM1Uyo1Uqoc"
    },
    {
      "artist": "Danakil",
      "album": "Dialogue de sourds",
      "track": "Marley",
      "uri": "spotify:track:0UZtknI7pCLAVGtHPLIYXZ"
    },
    {
      "artist": "Damso",
      "album": "Ipséité",
      "track": "Θ. Macarena",
      "uri": "spotify:track:2ewjMyCbNv2X1dB2qIDCwD"
    },
    {
      "artist": "Naps",
      "album": "On est fait pour ça",
      "track": "Fortuné",
      "uri": "spotify:track:7s0dmq8oMRJ4kVthfPk4O1"
    },
    {
      "artist": "La Caution",
      "album": "Peines de Maures / Arc-en-ciel pour daltoniens",
      "track": "Thé à la menthe",
      "uri": "spotify:track:2eDvflMCe9ssOkUJrxqikB"
    },
    {
      "artist": "Toploader",
      "album": "Onka's Big Moka",
      "track": "Dancing in the Moonlight",
      "uri": "spotify:track:3Fzlg5r1IjhLk2qRw667od"
    },
    {
      "artist": "Kanye West",
      "album": "Late Registration",
      "track": "Hey Mama",
      "uri": "spotify:track:46OFHBw45fNi7QNjSetITR"
    },
    {
      "artist": "XXXTENTACION",
      "album": "17",
      "track": "Revenge",
      "uri": "spotify:track:5TXDeTFVRVY7Cvt0Dw4vWW"
    },
    {
      "artist": "The Blessed Madonna",
      "album": "Mercy (feat. Jacob Lusk)",
      "track": "Mercy (feat. Jacob Lusk)",
      "uri": "spotify:track:4ejCsNXh66YasBUiwfBhDg"
    },
    {
      "artist": "Wu-Tang Clan",
      "album": "The W",
      "track": "Jah World (feat. Ghostface Killah, RZA & Junior Reid)",
      "uri": "spotify:track:5xmWmZCN4397q8qdwEnLqi"
    },
    {
      "artist": "Kanye West",
      "album": "Graduation",
      "track": "Can't Tell Me Nothing",
      "uri": "spotify:track:0mEdbdeRFQwBhN4xfyIeUM"
    },
    {
      "artist": "Kavinsky",
      "album": "Nightcall",
      "track": "Nightcall - Dustin N'Guyen Remix",
      "uri": "spotify:track:3uEwbhvBSlE3pWT9yQfC1P"
    },
    {
      "artist": "M.I.A.",
      "album": "Kala",
      "track": "Paper Planes",
      "uri": "spotify:track:1ixbwbeBi5ufN4noUKmW5a"
    },
    {
      "artist": "Heuss L'enfoiré",
      "album": "Saiyan",
      "track": "Saiyan",
      "uri": "spotify:track:63jpYDOn7xGEPzpUxViZu2"
    },
    {
      "artist": "The Rolling Stones",
      "album": "Aftermath",
      "track": "Paint It, Black",
      "uri": "spotify:track:63T7DJ1AFDD6Bn8VzG6JE8"
    },
    {
      "artist": "Amy Winehouse",
      "album": "Back To Black",
      "track": "You Know I'm No Good",
      "uri": "spotify:track:4zQuwW24dweWcaX0fEJkP2"
    },
    {
      "artist": "Etta James",
      "album": "Heart & Soul: A Retrospective",
      "track": "Something's Got A Hold On Me",
      "uri": "spotify:track:6EAlFsajDK1PVgfhdJbS5Y"
    },
    {
      "artist": "System Of A Down",
      "album": "Hypnotize",
      "track": "Lonely Day",
      "uri": "spotify:track:4xBHZ2Mr0gCdFYXrPZuYXO"
    },
    {
      "artist": "Chill Bump",
      "album": "Ego Trip",
      "track": "Not Today",
      "uri": "spotify:track:7rLPSqce44D3GQqcj7Cyh6"
    },
    {
      "artist": "Oxmo Puccino",
      "album": "Le cactus de Sibérie",
      "track": "Toucher l'horizon - Remasterisé",
      "uri": "spotify:track:1QZ66nuBGkHgb9WWGcXBte"
    },
    {
      "artist": "Kendrick Lamar",
      "album": "DAMN.",
      "track": "PRIDE.",
      "uri": "spotify:track:6IZvVAP7VPPnsGX6bvgkqg"
    },
    {
      "artist": "Manu Chao",
      "album": "Próxima Estación: Esperanza",
      "track": "Me Gustas Tu",
      "uri": "spotify:track:6b37xrsNCWYIUphFBazqD6"
    },
    {
      "artist": "Lenny Kravitz",
      "album": "Mama Said",
      "track": "It Ain't Over 'Til It's Over",
      "uri": "spotify:track:6VnpKLtfNH4Dk09YSGPSyR"
    },
    {
      "artist": "Trinix Remix",
      "album": "Asibe Happy",
      "track": "Asibe Happy",
      "uri": "spotify:track:7pxyrmw6xrmjRCxMSgGhLK"
    },
    {
      "artist": "Josman",
      "album": "J.000.$",
      "track": "Les Flammes",
      "uri": "spotify:track:4i6CKsl0vgzFF97h5nzpS3"
    },
    {
      "artist": "Suprême NTM",
      "album": "Suprême NTM",
      "track": "Seine Saint-Denis Style",
      "uri": "spotify:track:1NNAoUoADTegqQqbKOyIQv"
    },
    {
      "artist": "Llaurensy",
      "album": "Balad To a Mexican Desert",
      "track": "Balad To a Mexican Desert - Rework",
      "uri": "spotify:track:5kUDoyDvVPSSj08t50CJu2"
    },
    {
      "artist": "Daft Punk",
      "album": "Discovery",
      "track": "Something About Us",
      "uri": "spotify:track:1NeLwFETswx8Fzxl2AFl91"
    },
    {
      "artist": "Elliott Smith",
      "album": "Either/Or",
      "track": "Between The Bars",
      "uri": "spotify:track:52Bg6oaos7twR7IUtEpqcE"
    },
    {
      "artist": "Red Hot Chili Peppers",
      "album": "Blood Sugar Sex Magik",
      "track": "Under the Bridge",
      "uri": "spotify:track:3d9DChrdc6BOeFsbrZ3Is0"
    },
    {
      "artist": "Bob Marley & The Wailers",
      "album": "Exodus",
      "track": "Natural Mystic",
      "uri": "spotify:track:5uqQyRJV8qLt8zEqnvsBVK"
    },
    {
      "artist": "Metro Boomin",
      "album": "HEROES & VILLAINS",
      "track": "Superhero (Heroes & Villains) [with Future & Chris Brown]",
      "uri": "spotify:track:70UV1HmppYUxBI6yCev4d5"
    },
    {
      "artist": "Kanye West",
      "album": "Graduation",
      "track": "Homecoming",
      "uri": "spotify:track:4iz9lGMjU1lXS51oPmUmTe"
    },
    {
      "artist": "Booba",
      "album": "Ouest Side",
      "track": "Pitbull",
      "uri": "spotify:track:1efBNlkIwBbccMBXHoJBZN"
    },
    {
      "artist": "A$AP Rocky",
      "album": "TESTING",
      "track": "Praise The Lord (Da Shine) (feat. Skepta)",
      "uri": "spotify:track:7ycWLEP1GsNjVvcjawXz3z"
    },
    {
      "artist": "Trinix Remix",
      "album": "Rosa (Que Linda Eres)",
      "track": "Rosa (Que Linda Eres)",
      "uri": "spotify:track:5hRvYEY8c4EKLwYo9DNUWs"
    },
    {
      "artist": "Aaron May",
      "album": "CHASE",
      "track": "I'm Good Luv, Enjoy.",
      "uri": "spotify:track:3RKLJPyyMZfwebsePAzqjL"
    },
    {
      "artist": "Emma Peters",
      "album": "Scoot",
      "track": "Scoot",
      "uri": "spotify:track:0BWHEpxLHY3SwRDUhh6R8a"
    },
    {
      "artist": "Etta James",
      "album": "Tubes pour danser - Années 60",
      "track": "At Last",
      "uri": "spotify:track:4nQgdtwxZOyKA0oBdkZfXa"
    },
    {
      "artist": "PLK",
      "album": "2069'",
      "track": "Demain",
      "uri": "spotify:track:66TAAKeoOD0cFpVRug9IXZ"
    },
    {
      "artist": "Booba",
      "album": "Lunatic",
      "track": "Comme une étoile",
      "uri": "spotify:track:0lor8cLolD2FFFckNlaCPk"
    },
    {
      "artist": "Oliver Heldens",
      "album": "Mas Que Nada",
      "track": "Mas Que Nada",
      "uri": "spotify:track:6yW6Q8ZPgDBQA1yHWL4Jmh"
    },
    {
      "artist": "So Far So Good",
      "album": "Dystopia",
      "track": "Dystopia",
      "uri": "spotify:track:2ni6wXwpRS6SxPtRzd6lNC"
    },
    {
      "artist": "Kanye West",
      "album": "My Beautiful Dark Twisted Fantasy",
      "track": "Dark Fantasy",
      "uri": "spotify:track:7yNK27ZTpHew0c55VvIJgm"
    },
    {
      "artist": "Black Pumas",
      "album": "Black Pumas",
      "track": "Colors",
      "uri": "spotify:track:6J3HNhDBIwEX11bX8hzx5u"
    },
    {
      "artist": "Schur",
      "album": "The Unsure Mixtape",
      "track": "Timezones",
      "uri": "spotify:track:5aSeyhSp2qxYr8yBCtPNvr"
    },
    {
      "artist": "Akshin Alizadeh",
      "album": "Broken Keys",
      "track": "Broken Keys",
      "uri": "spotify:track:1UvhMXB2UNVPX3q2dyzSL1"
    },
    {
      "artist": "Dave",
      "album": "Sprinter",
      "track": "Sprinter",
      "uri": "spotify:track:2FDTHlrBguDzQkp7PVj16Q"
    },
    {
      "artist": "Radiohead",
      "album": "OK Computer",
      "track": "Exit Music (For A Film)",
      "uri": "spotify:track:0z1o5L7HJx562xZSATcIpY"
    },
    {
      "artist": "Future",
      "album": "FUTURE",
      "track": "Mask Off",
      "uri": "spotify:track:0VgkVdmE4gld66l8iyGjgx"
    },
    {
      "artist": "Drake",
      "album": "Back To Back",
      "track": "Back To Back",
      "uri": "spotify:track:5lFDtgWsjRJu8fPOAyJIAK"
    },
    {
      "artist": "Jul",
      "album": "Cœur blanc",
      "track": "Cœur blanc",
      "uri": "spotify:track:5BwdbhIcQPWM7Vpo9ggAsx"
    },
    {
      "artist": "Booba",
      "album": "Leo Messi",
      "track": "Leo Messi",
      "uri": "spotify:track:3YZdPvENFPytMyrnkRWm1B"
    },
    {
      "artist": "Diddy",
      "album": "The Saga Continues...",
      "track": "Bad Boy for Life",
      "uri": "spotify:track:2eOuL8KesslTLQERQPu11D"
    },
    {
      "artist": "Boney M.",
      "album": "Take The Heat Off Me",
      "track": "Sunny",
      "uri": "spotify:track:3pf96IFggfQuT6Gafqx2rt"
    },
    {
      "artist": "Estelle",
      "album": "Shine",
      "track": "American Boy",
      "uri": "spotify:track:6etwirSInfuJrSOlogS6Sh"
    },
    {
      "artist": "Kavinsky",
      "album": "OutRun",
      "track": "Roadgame",
      "uri": "spotify:track:7D1Dq1oEmlKNJltvzTL0wN"
    },
    {
      "artist": "Kanye West",
      "album": "True Love",
      "track": "True Love",
      "uri": "spotify:track:06JvOZ39sK8D8SqiqfaxDU"
    },
    {
      "artist": "Mac Miller",
      "album": "The Divine Feminine",
      "track": "Dang! (feat. Anderson .Paak)",
      "uri": "spotify:track:5iUQMwxUPdJBFeGkePtM66"
    },
    {
      "artist": "21 Savage",
      "album": "american dream",
      "track": "redrum",
      "uri": "spotify:track:52eIcoLUM25zbQupAZYoFh"
    },
    {
      "artist": "Daft Punk",
      "album": "Random Access Memories",
      "track": "Instant Crush (feat. Julian Casablancas)",
      "uri": "spotify:track:2cGxRwrMyEAp8dEbuZaVv6"
    },
    {
      "artist": "Cage The Elephant",
      "album": "Cage The Elephant",
      "track": "Ain't No Rest For The Wicked - Original Version",
      "uri": "spotify:track:7tCHpjktA50ihtkLz6bAnn"
    },
    {
      "artist": "Lomepal",
      "album": "Jeannine",
      "track": "Trop beau",
      "uri": "spotify:track:4WB9OeauHXnGOMUK4s80gM"
    },
    {
      "artist": "Salt-N-Pepa",
      "album": "Very Necessary",
      "track": "Shoop",
      "uri": "spotify:track:0Pu71wxadDlB8fJXfjIjeJ"
    },
    {
      "artist": "BigXthaPlug",
      "album": "AMAR",
      "track": "Texas",
      "uri": "spotify:track:7j7ud2oFTJ8BjmeI8bjkQm"
    },
    {
      "artist": "Linkin Park",
      "album": "One More Light",
      "track": "One More Light",
      "uri": "spotify:track:3xXBsjrbG1xQIm1xv1cKOt"
    },
    {
      "artist": "Folamour",
      "album": "Manifesto",
      "track": "Fearless",
      "uri": "spotify:track:4zidWR4YDfTFTK4M1PCZ0R"
    },
    {
      "artist": "Jul",
      "album": "Dans ma paranoïa",
      "track": "J'oublie tout",
      "uri": "spotify:track:0SKNkEMV313mE6oYsgVCgm"
    },
    {
      "artist": "Eminem",
      "album": "Encore",
      "track": "Mockingbird",
      "uri": "spotify:track:561jH07mF1jHuk7KlaeF0s"
    },
    {
      "artist": "Pink Floyd",
      "album": "Wish You Were Here",
      "track": "Wish You Were Here - 2011 Remaster",
      "uri": "spotify:track:7aE5WXu5sFeNRh3Z05wwu4"
    },
    {
      "artist": "Papooz",
      "album": "Papooz",
      "track": "Ulysses and the Sea",
      "uri": "spotify:track:1YmPS3jF3RMCTajDYgTD2q"
    },
    {
      "artist": "Le Dé",
      "album": "Delta Plane",
      "track": "Espace temps",
      "uri": "spotify:track:5gBZ0oJ7aGFIJtbBRRT3SO"
    },
    {
      "artist": "Forrest Frank",
      "album": "UP!",
      "track": "UP!",
      "uri": "spotify:track:50utqknCBo0N3QAQbXIPKV"
    },
    {
      "artist": "Meek Mill",
      "album": "Championships",
      "track": "Going Bad (feat. Drake)",
      "uri": "spotify:track:2IRZnDFmlqMuOrYOLnZZyc"
    },
    {
      "artist": "The White Stripes",
      "album": "Elephant",
      "track": "Seven Nation Army",
      "uri": "spotify:track:3dPQuX8Gs42Y7b454ybpMR"
    },
    {
      "artist": "Werenoi",
      "album": "Telegram",
      "track": "Solitaire",
      "uri": "spotify:track:3kzXT2poHInDISrXOgT1PR"
    },
    {
      "artist": "Dinos",
      "album": "Taciturne",
      "track": "XNXX",
      "uri": "spotify:track:352VLwRsxtqor8YTaJPYYz"
    },
    {
      "artist": "Sean Kingston",
      "album": "Beautiful Girls",
      "track": "Beautiful Girls",
      "uri": "spotify:track:1hGy2eLcmC8eKx7qr1tOqx"
    },
    {
      "artist": "Elton John",
      "album": "Too Low For Zero",
      "track": "I'm Still Standing",
      "uri": "spotify:track:1jDJFeK9x3OZboIAHsY9k2"
    },
    {
      "artist": "Pochill",
      "album": "Nothing But the Hill",
      "track": "Porqué",
      "uri": "spotify:track:2Ugai6hCz9h8K6lAZ0XP49"
    },
    {
      "artist": "George Michael",
      "album": "Ladies And Gentlemen... The Best Of George Michael",
      "track": "Careless Whisper",
      "uri": "spotify:track:4jDmJ51x1o9NZB5Nxxc7gY"
    },
    {
      "artist": "Lomepal",
      "album": "Jeannine",
      "track": "Évidemment",
      "uri": "spotify:track:43yYuYeSOOupBHOkH9pRtF"
    },
    {
      "artist": "Ninho",
      "album": "NI",
      "track": "Eurostar (feat. Central Cee)",
      "uri": "spotify:track:3Iy4j2lCqW8BXGkFk21U6F"
    },
    {
      "artist": "Kanye West",
      "album": "808s & Heartbreak",
      "track": "Heartless",
      "uri": "spotify:track:4EWCNWgDS8707fNSZ1oaA5"
    },
    {
      "artist": "MHD",
      "album": "Full",
      "track": "Full",
      "uri": "spotify:track:1hZyHAA9e0G0eQ2WSNHkfM"
    },
    {
      "artist": "Gorillaz",
      "album": "Gorillaz",
      "track": "Clint Eastwood",
      "uri": "spotify:track:1RKUoGiLEbcXN4GY4spQDx"
    },
    {
      "artist": "Werenoi",
      "album": "Scarface",
      "track": "Scarface",
      "uri": "spotify:track:2RSpOGQtcNgmbx5ejgho5X"
    },
    {
      "artist": "Mister You",
      "album": "Hasta la muerte",
      "track": "Ma vie",
      "uri": "spotify:track:4L8kECUUhKcCKa1u69NR7g"
    },
    {
      "artist": "Frank Sinatra",
      "album": "Nothing But The Best",
      "track": "My Way - 2008 Remastered",
      "uri": "spotify:track:2YkIDPL5lGhRhomCq4S2RO"
    },
    {
      "artist": "Frank Sinatra",
      "album": "That's Life",
      "track": "That's Life",
      "uri": "spotify:track:4FmCUATNIarCQh72JYdvnm"
    },
    {
      "artist": "JeanJass",
      "album": "Goldman",
      "track": "Mes jambes",
      "uri": "spotify:track:5XfSZSiHb3NzgawUXZGA40"
    },
    {
      "artist": "CaptainSpaceTime",
      "album": "Tryin' to Stay Alive",
      "track": "Tryin' to Stay Alive",
      "uri": "spotify:track:7vwlPp1eAXUSqNhBGJEvkX"
    },
    {
      "artist": "Yung Lean",
      "album": "Lavender",
      "track": "Ginseng Strip 2002",
      "uri": "spotify:track:7v3rmoy5jcn4h5UqwQyCM3"
    },
    {
      "artist": "Bill Withers",
      "album": "Just As I Am",
      "track": "Ain't No Sunshine",
      "uri": "spotify:track:1k1Bqnv2R0uJXQN4u6LKYt"
    },
    {
      "artist": "Chuck Berry",
      "album": "Berry Is On Top",
      "track": "Johnny B. Goode",
      "uri": "spotify:track:2QfiRTz5Yc8DdShCxG1tB2"
    },
    {
      "artist": "Silver",
      "album": "Silver",
      "track": "Wham Bam Shang-A-Lang",
      "uri": "spotify:track:3qrEG6rQ9Qm72MNWeUKKiU"
    },
    {
      "artist": "Nèg' Marrons",
      "album": "Le Bilan",
      "track": "Le bilan",
      "uri": "spotify:track:4hElE1DmCfpoFVjczvfB5U"
    },
    {
      "artist": "Rim'K",
      "album": "Mutant",
      "track": "Insomnie",
      "uri": "spotify:track:4F3lwXIP6DbHMeoGebCDBs"
    },
    {
      "artist": "Kavinsky",
      "album": "OutRun",
      "track": "Odd Look",
      "uri": "spotify:track:3T1CEAG5ukgdqGvQuXWzqI"
    },
    {
      "artist": "Travis Scott",
      "album": "ASTROWORLD",
      "track": "SICKO MODE",
      "uri": "spotify:track:2xLMifQCjDGFmkHkpNLD9h"
    },
    {
      "artist": "Arctic Monkeys",
      "album": "Favourite Worst Nightmare",
      "track": "505",
      "uri": "spotify:track:0BxE4FqsDD1Ot4YuBXwAPp"
    },
    {
      "artist": "Damso",
      "album": "Ipséité",
      "track": "N. J Respect R",
      "uri": "spotify:track:539zyjwDE87Cjp1mzRN8H7"
    },
    {
      "artist": "Zaho de Sagazan",
      "album": "La symphonie des éclairs",
      "track": "La symphonie des éclairs",
      "uri": "spotify:track:4QIH0XYnCLoCl1WZIV08Pn"
    },
    {
      "artist": "Gwen Stefani",
      "album": "The Sweet Escape",
      "track": "The Sweet Escape",
      "uri": "spotify:track:07K4GcCDSTiXUF5ssyTRUM"
    },
    {
      "artist": "Lil Nas X",
      "album": "7",
      "track": "Old Town Road",
      "uri": "spotify:track:0F7FA14euOIX8KcbEturGH"
    },
    {
      "artist": "Electric Light Orchestra",
      "album": "Out of the Blue",
      "track": "Mr. Blue Sky",
      "uri": "spotify:track:2RlgNHKcydI9sayD2Df2xp"
    },
    {
      "artist": "Boney M.",
      "album": "Daddy Cool",
      "track": "Rasputin",
      "uri": "spotify:track:5lWSa1rmuSL6OBPOnkAqoa"
    },
    {
      "artist": "Lomepal",
      "album": "Jeannine",
      "track": "Mômes",
      "uri": "spotify:track:2FRnrkO72S9tbqu6eLjq6b"
    },
    {
      "artist": "50 Cent",
      "album": "Get Rich Or Die Tryin'",
      "track": "In Da Club",
      "uri": "spotify:track:7iL6o9tox1zgHpKUfh9vuC"
    },
    {
      "artist": "Frank Watkinson",
      "album": "Creep",
      "track": "Creep",
      "uri": "spotify:track:1JZs8y93ijxXKrZQEROaXD"
    },
    {
      "artist": "alt-J",
      "album": "This Is All Yours",
      "track": "Left Hand Free",
      "uri": "spotify:track:5qJqzpNdEbt92roedFwoDR"
    },
    {
      "artist": "Prodigy",
      "album": "GAME OVER II",
      "track": "MOBB NIGGAZ",
      "uri": "spotify:track:0HCRi7rgzlTK09lQjeqNYN"
    },
    {
      "artist": "Pusha T",
      "album": "Still Ya Pusha",
      "track": "Sure Thing - Remix",
      "uri": "spotify:track:6iclNZVKDyJwVXTjxHUWaV"
    },
    {
      "artist": "Jul",
      "album": "La zone en personne",
      "track": "Pour un violet",
      "uri": "spotify:track:4YxgYZJeC91vmJrDRdfnZG"
    }
  ],
  "albums": [
  ],
  "shows": [
  ],
  "episodes": [
    {
      "name": "What So Not - Touched (Slumberjack Remix)",
      "show": "LVBEL C5 CASHFLOW - BABA",
      "uri": "spotify:episode:3MxDm8VIU9z6uzA4QT5kZZ"
    }
  ],
  "bannedTracks": [
  ],
  "artists": [
    {
      "name": "20syl",
      "uri": "spotify:artist:6mA4csYsYvf4Mq02PleZEV"
    },
    {
      "name": "AC/DC",
      "uri": "spotify:artist:711MCceyCBcFnzjGY4Q7Un"
    },
    {
      "name": "Booba",
      "uri": "spotify:artist:58wXmynHaAWI5hwlPZP3qL"
    },
    {
      "name": "Coldplay",
      "uri": "spotify:artist:4gzpq5DPGxSnKTe4SA8HAU"
    },
    {
      "name": "Daft Punk",
      "uri": "spotify:artist:4tZwfgrHOc3mvqYlEYSvVi"
    },
    {
      "name": "Davodka",
      "uri": "spotify:artist:3viUmbbKSqgMFOVHfrZQpn"
    },
    {
      "name": "Elliott Smith",
      "uri": "spotify:artist:2ApaG60P4r0yhBoDCGD8YG"
    },
    {
      "name": "Gorillaz",
      "uri": "spotify:artist:3AA28KZvwAUcZuOKwyblJQ"
    },
    {
      "name": "Kanye West",
      "uri": "spotify:artist:5K4W6rqBFWDnAN6FQUkS6x"
    },
    {
      "name": "Kendrick Lamar",
      "uri": "spotify:artist:2YZyLoL8N0Wb9xBt1NhZWg"
    },
    {
      "name": "Linkin Park",
      "uri": "spotify:artist:6XyY86QOPPrYVGvF9ch6wz"
    },
    {
      "name": "Lomepal",
      "uri": "spotify:artist:1Yfe3ONJlioHys7jwHdfVm"
    },
    {
      "name": "dj spizike",
      "uri": "spotify:artist:24k3vSCXZUr1KNu8DbvQGm"
    }
  ],
  "bannedArtists": [
  ],
  "other": [
  ]
}